{
  "version": 1,
  "id": "tango-6x6-537",
  "size": 6,
  "rules": {
    "balance": true,
    "maxAdjacent": 2
  },
  "givens": [
    {
      "r": 0,
      "c": 1,
      "value": "moon"
    },
    {
      "r": 0,
      "c": 3,
      "value": "sun"
    },
    {
      "r": 0,
      "c": 4,
      "value": "sun"
    },
    {
      "r": 1,
      "c": 5,
      "value": "moon"
    },
    {
      "r": 2,
      "c": 2,
      "value": "moon"
    },
    {
      "r": 3,
      "c": 2,
      "value": "moon"
    },
    {
      "r": 4,
      "c": 5,
      "value": "sun"
    },
    {
      "r": 5,
      "c": 5,
      "value": "sun"
    }
  ],
  "relations": [
    {
      "r": 0,
      "c": 1,
      "dir": "down",
      "type": "different"
    },
    {
      "r": 0,
      "c": 2,
      "dir": "right",
      "type": "different"
    },
    {
      "r": 0,
      "c": 3,
      "dir": "down",
      "type": "different"
    },
    {
      "r": 1,
      "c": 1,
      "dir": "down",
      "type": "different"
    },
    {
      "r": 3,
      "c": 2,
      "dir": "down",
      "type": "different"
    },
    {
      "r": 4,
      "c": 2,
      "dir": "down",
      "type": "same"
    },
    {
      "r": 4,
      "c": 4,
      "dir": "right",
      "type": "different"
    },
    {
      "r": 5,
      "c": 1,
      "dir": "right",
      "type": "same"
    },
    {
      "r": 5,
      "c": 4,
      "dir": "right",
      "type": "different"
    }
  ],
  "solution": [
    "SMMSSM",
    "MSSMSM",
    "SMMSMS",
    "SMMSSM",
    "MSSMMS",
    "MSSMMS"
  ],
  "difficulty": {
    "label": "hard",
    "score": 138,
    "techniques": [
      "relation",
      "triple"
    ],
    "searchNodes": 3,
    "seed": 1773119888523898584
  }
}
