{
  "version": 1,
  "id": "tango-6x6-612",
  "size": 6,
  "rules": {
    "balance": true,
    "maxAdjacent": 2
  },
  "givens": [
    {
      "r": 0,
      "c": 1,
      "value": "sun"
    },
    {
      "r": 0,
      "c": 4,
      "value": "sun"
    },
    {
      "r": 1,
      "c": 0,
      "value": "moon"
    },
    {
      "r": 2,
      "c": 4,
      "value": "moon"
    },
    {
      "r": 2,
      "c": 5,
      "value": "moon"
    },
    {
      "r": 3,
      "c": 1,
      "value": "moon"
    },
    {
      "r": 4,
      "c": 0,
      "value": "moon"
    },
    {
      "r": 4,
      "c": 3,
      "value": "moon"
    },
    {
      "r": 4,
      "c": 5,
      "value": "sun"
    }
  ],
  "relations": [
    {
      "r": 0,
      "c": 0,
      "dir": "down",
      "type": "different"
    },
    {
      "r": 0,
      "c": 1,
      "dir": "right",
      "type": "different"
    },
    {
      "r": 0,
      "c": 2,
      "dir": "right",
      "type": "same"
    },
    {
      "r": 0,
      "c": 4,
      "dir": "right",
      "type": "different"
    },
    {
      "r": 2,
      "c": 5,
      "dir": "down",
      "type": "different"
    },
    {
      "r": 3,
      "c": 0,
      "dir": "down",
      "type": "same"
    },
    {
      "r": 4,
      "c": 4,
      "dir": "right",
      "type": "same"
    },
    {
      "r": 5,
      "c": 2,
      "dir": "right",
      "type": "same"
    }
  ],
  "solution": [
    "SSMMSM",
    "MMSMSS",
    "SSMSMM",
    "MMSSMS",
    "MSMMSS",
    "SMSSMM"
  ],
  "difficulty": {
    "label": "hard",
    "score": 139,
    "techniques": [
      "line-candidate",
      "relation",
      "triple"
    ],
    "searchNodes": 3,
    "seed": 1773119888524492509
  }
}
